amazon_purchase.py
amazon_purchase-1.0.0.dist-info/METADATA
amazon_purchase-1.0.0.dist-info/WHEEL
amazon_purchase-1.0.0.dist-info/licenses/LICENSE
amazon_purchase-1.0.0.dist-info/RECORD
